HISTORY.rst
LICENSE
MANIFEST.in
README-ja.rst
README.md
README.rst
setup.cfg
setup.py
tox.ini
django_spine.egg-info/PKG-INFO
django_spine.egg-info/SOURCES.txt
django_spine.egg-info/dependency_links.txt
django_spine.egg-info/requires.txt
django_spine.egg-info/top_level.txt
docs/Makefile
docs/make.bat
docs/build/doctrees/HISTORY.doctree
docs/build/doctrees/environment.pickle
docs/build/doctrees/index.doctree
docs/build/doctrees/usage.doctree
docs/build/html/.buildinfo
docs/build/html/HISTORY.html
docs/build/html/genindex.html
docs/build/html/index.html
docs/build/html/objects.inv
docs/build/html/search.html
docs/build/html/searchindex.js
docs/build/html/usage.html
docs/build/html/_sources/HISTORY.txt
docs/build/html/_sources/index.txt
docs/build/html/_sources/usage.txt
docs/build/html/_static/ajax-loader.gif
docs/build/html/_static/basic.css
docs/build/html/_static/comment-bright.png
docs/build/html/_static/comment-close.png
docs/build/html/_static/comment.png
docs/build/html/_static/dialog-note.png
docs/build/html/_static/dialog-seealso.png
docs/build/html/_static/dialog-topic.png
docs/build/html/_static/dialog-warning.png
docs/build/html/_static/doctools.js
docs/build/html/_static/down-pressed.png
docs/build/html/_static/down.png
docs/build/html/_static/epub.css
docs/build/html/_static/file.png
docs/build/html/_static/footerbg.png
docs/build/html/_static/headerbg.png
docs/build/html/_static/ie6.css
docs/build/html/_static/jquery.js
docs/build/html/_static/middlebg.png
docs/build/html/_static/minus.png
docs/build/html/_static/plus.png
docs/build/html/_static/pygments.css
docs/build/html/_static/pyramid.css
docs/build/html/_static/searchtools.js
docs/build/html/_static/transparent.gif
docs/build/html/_static/underscore.js
docs/build/html/_static/up-pressed.png
docs/build/html/_static/up.png
docs/build/html/_static/websupport.js
docs/source/HISTORY.rst
docs/source/conf.py
docs/source/index.rst
docs/source/usage.rst
examples/.DS_Store
examples/django_spine/manage.py
examples/django_spine/set.sh
examples/django_spine/unset.sh
examples/django_spine/django_spine/__init__.py
examples/django_spine/django_spine/__init__.pyc
