Metadata-Version: 1.1
Name: django-spine
Version: 0.3.3
Summary: Spine plugin for Django
Home-page: https://github.com/ikeikeikeike/django-spine
Author: Tatsuo Ikeda
Author-email: jp.ne.co.jp at gmail
License: MIT License
Keywords: javascript,coffeescript,django,spine
Platform: UNKNOWN
Classifier: Development Status :: 4 - Beta
Classifier: Framework :: Django
Classifier: Environment :: Console
Classifier: Environment :: Web Environment
Classifier: Intended Audience :: Developers
Classifier: License :: OSI Approved :: MIT License
Classifier: Programming Language :: Python :: 2.6
Classifier: Programming Language :: Python :: 2.7
Classifier: Topic :: Utilities
Classifier: Topic :: Software Development :: Libraries :: Python Modules
